Testbenchs/CPU/test.v
`timescale 1ns / 1ps



module AddSub(
    input [15:0] buswires_A,
    input [15:0] raout,

    // select
    input sub,
    output [15:0] result
);
    wire [15:0]b_xor_sub;
    wire carry_in;


    assign b_xor_sub = buswires_A ^ {16{sub}}; // 16'b sub, so bu 2 0xFFFF
    assign carry_in = sub;
    assign result = (raout + b_xor_sub + carry_in);   // raout +- buswires

endmodule



// Toan tu cong hoac tru
module ALU_16bit(
    input clk,
    input [15:0] buswires,

    // control
    input ain, // enable A
    input gin, // enable B
    input sub,        // Control: 0 (Add), 1 (Sub)

    output [15:0] aluout // Output 
);
    wire [15:0] raout, result;
    


    register_16bit reg_a (
            .clk(clk),
            .rin(ain),
            .buswires(buswires),
            .Rout(raout)
        );


    // AddSub
    AddSub addsub (
        .buswires_A(buswires),
        .raout(raout),
        .sub(sub),
        .result(result)
    );



    register_16bit reg_g (
            .clk(clk),
            .rin(gin),
            .buswires(result),
            .Rout(aluout)
        );



endmodule

module IR(
    input [15:0] din,
    input IRin,
    input clk,
    output reg [8:0] IR_out
);
    always @(posedge clk) begin
        if (IRin) begin
          IR_out <= din[8:0];
        end
    end


endmodule


module CU(
    // input
    input run,
    input resetn,
    input [8:0]IR,      // 9 bit
    input [1:0]state,   // 2 bit, PC

    // output
    output reg IRin,        // enable IR

    output reg [7:0] rin,   // enable register r0 -> r7

    output reg [2:0]rout,   // Select register (mux)
    output reg din_enable,  // Mux
    output reg gout,        // select ALU out (Mux)

    output reg ain,         // ALU, enable a
    output reg gin,         // ALU, enable g
    output reg sub,         // ALU, select sub or add
    
    output reg clear,       // clear counter
    output reg done         // complete
);

wire [2:0] opcode = IR[8:6];
wire [2:0] rx = IR[5:3];
wire [2:0] ry = IR[2:0];
reg [15:0] buswires;


// Sequential Control 16-bit CPU

localparam mv  = 3'b000;    // move rx, ry
localparam mvi = 3'b001;    // move rx, din
localparam add_state = 3'b010;    // add rx, rx, ry
localparam sub_state = 3'b011;    // sub rx, rx, ry
// localparam mvo = 3'b100;    // move dout, rx


// chu ki hoat dong
localparam state_0 = 2'b00;
localparam state_1 = 2'b01;
localparam state_2 = 2'b10;
localparam state_3 = 2'b11;


always @(*) begin
    //

    if (!resetn) begin
        IRin = 0;
        rin = 0;
        rout = 0;
        gout = 0;
        ain = 0;
        gin = 0;
        sub = 0;
        din_enable = 0;
        clear = 1;
        done = 0;
    end

    else if (!run) begin
        IRin = IRin;
        rin = rin;
        rout = rout;
        din_enable = din_enable;
        gout = gout;
        ain = ain;
        gin = gin;
        sub = sub;
        clear = clear;
        done = done;
        end

    else begin
        clear = 0;
        done = 0;
            case (state) 
                state_0: begin
                    IRin = 1; // enable IR
                    clear = 0;
                    din_enable = 0;
                    ain = 0;
                    gin = 0;
                    gout = 0;
                    done = 0;
                    sub = 0;
                end

                state_1: begin
                            case (opcode)
                                mv: begin    
                                    rout = ry;
                                    rin  = rin_mux(rx);
                                    clear = 1;
                                    din_enable = 0;
                                    done = 1;
                                    
                                end

                                mvi: begin
                                    rout = rx;
                                    rin = rin_mux(rx);
                                    clear = 1;
                                    din_enable = 1;
                                    done = 1;
                                end

                                add_state, sub_state: begin
                                    rout = rx;
                                    rin  = rin_mux(rx);
                                    ain = 1;
                                    gin = 0;
                                    IRin = 0;
                                end

                                default: begin
                                $display("None values");
                                end

                            endcase
                end

                state_2: begin
                            // add
                        if (opcode == add_state || opcode == sub_state) begin
                                ain = 0;
                                rout = ry;
                                sub = (opcode == sub_state) ? 1 : 0; // if opcode == sub_state => sub = 1, else sub = 0
                                gin = 1;
                        
                        end

                        else begin
                            $display("None any values.");
                        end
                end

                state_3: begin
                        rin = rin_mux(rx);
                        gout=1;
                        clear = 1;
                        done=1;
                        ain = 0;
                        gin = 0;
                        rout = rx;
                end


                default: begin
                    $display("Invalid opcode: %b", state);
                end
            endcase
    end


end

  

// Choose registers
function [7:0] rin_mux(input [2:0]rx);
        case (rx)
        3'b000: rin_mux = 8'b00000001;
        3'b001: rin_mux = 8'b00000010;
        3'b010: rin_mux = 8'b00000100;
        3'b011: rin_mux = 8'b00001000;
        3'b100: rin_mux = 8'b00010000;
        3'b101: rin_mux = 8'b00100000;
        3'b110: rin_mux = 8'b01000000;
        3'b111: rin_mux = 8'b10000000;
        default: $display("None initial values in this module");
        endcase
endfunction



endmodule


module mux_8to1_16bit (
    /// data in
    // the data_ins of the registers 
    input [15:0]r0,
    input [15:0]r1,
    input [15:0]r2,
    input [15:0]r3,
    input [15:0]r4,
    input [15:0]r5,
    input [15:0]r6,
    input [15:0]r7,
    // the output of the ALU
    input [15:0]aluout,
     // data in
    input [15:0]din,



    /// select pints

    // select ALU out
    input gout,
    input [2:0] rout,   // select registers
    input din_enable,   // select din

    /// data out
    output reg [15:0] buswires

);

always @(*) begin
    if (din_enable) begin
        buswires = din;
    end

    else if (gout) begin
        buswires = aluout;
    end

    else begin
        case (rout)
        
            3'b000: buswires = r0;     // choose r0
            3'b001: buswires = r1;     // choose r1
            3'b010: buswires = r2;     // choose r2
            3'b011: buswires = r3;     // choose r3
            3'b100: buswires = r4;     // choose r4
            3'b101: buswires = r5;     // choose r5
            3'b110: buswires = r6;     // choose r6
            3'b111: buswires = r7;     // choose r7

            default: buswires = buswires;
        endcase
    end
end

 

endmodule


module PC_2bit (
    input clk,
    input clr,
    output reg [1:0] state
);
    
    always @(posedge clk) begin
        if (clr) begin
            state <= 2'b00;
        end 

        else begin
            state <= state + 1'b1;
        end
    end

   
endmodule


module register_16bit(
    input clk,
    // enable pins
    input rin,
    // data in
    input [15:0] buswires,
    // data out
    output reg [15:0] Rout
);

    always @(posedge clk) begin
       if (rin) begin
         Rout <= buswires;  // Gán giá trị từ buswires vào Rout
       end

       else begin
         Rout <= Rout;
       end
    end 

  
endmodule

module CPU_16bit(
    input run,
    input resetn,
    input clk,
    input [15:0] din,

    output [15:0] buswires,
    output done
);


// Multiplexer 8 to 1
wire [2:0] rout;
wire din_enable;
wire gout;
wire [15:0] r0;
wire [15:0] r1;
wire [15:0] r2;
wire [15:0] r3;
wire [15:0] r4;
wire [15:0] r5;
wire [15:0] r6;
wire [15:0] r7;


// ALU
wire ain;
wire sub;
wire gin;
wire [15:0] aluout;

// register
wire [7:0]rin;


// intrustion register
wire IRin;
wire [8:0] IR;

// Counter
wire clear;
wire [1:0] state;

ALU_16bit ALU_16bit(
    .clk(clk),
    .buswires(buswires),
    .ain(ain),
    .gin(gin),
    .sub(sub),
    .aluout(aluout)
);

IR intr_reg(
    .clk(clk),
    .din(din),
    .IRin(IRin),
    .IR_out(IR)
);

mux_8to1_16bit mux(
    .rout(rout),
    .gout(gout),
    .din_enable(din_enable),
    .r0(r0),
    .r1(r1),
    .r2(r2),
    .r3(r3),
    .r4(r4),
    .r5(r5),
    .r6(r6),
    .r7(r7),
    .din(din),
    .aluout(aluout),
    .buswires(buswires)
);

// Register 0
register_16bit register0(
    .clk(clk),
    .rin(rin[0]),
    .buswires(buswires),
    .Rout(r0)
);
// Register 1
register_16bit register1(
    .clk(clk),
    .rin(rin[1]),
    .buswires(buswires),
    .Rout(r1)
);
// Register 2
register_16bit register2(
    .clk(clk),
    .rin(rin[2]),
    .buswires(buswires),
    .Rout(r2)
);
// Register 3
register_16bit register3(
    .clk(clk),
    .rin(rin[3]),
    .buswires(buswires),
    .Rout(r3)
);
// Register 4
register_16bit register4(
    .clk(clk),
    .rin(rin[4]),
    .buswires(buswires),
    .Rout(r4)
);
// Register 5
register_16bit register5(
    .clk(clk),
    .rin(rin[5]),
    .buswires(buswires),
    .Rout(r5)
);
// Register 6
register_16bit register6(
    .clk(clk),
    .rin(rin[6]),
    .buswires(buswires),
    .Rout(r6)
);
// Register 7
register_16bit register7(
    .clk(clk),
    .rin(rin[7]),
    .buswires(buswires),
    .Rout(r7)
);


PC_2bit counter_2bit(
    .clk(clk),
    .clr(clear),
    .state(state)
);

CU control_unit(
    .run(run),
    .resetn(resetn),
    .IR(IR),
    .state(state),
    .IRin(IRin),
    .rin(rin),
    .rout(rout),
    .din_enable(din_enable),
    .gout(gout),
    .ain(ain),
    .gin(gin),
    .sub(sub),
    .clear(clear),
    .done(done)
);



endmodule

Testbenchs/Mux_8to1_16bit/mux_8to1_16bit_tb.vcd
$date
	Wed Jan 29 22:17:35 2025
$end
$version
	Icarus Verilog
$end
$timescale
	1ps
$end
$scope module mux_8to1_16bit $end
$var wire 16 ! aluout [15:0] $end
$var wire 16 " din [15:0] $end
$var wire 1 # din_enable $end
$var wire 1 $ gout $end
$var wire 16 % r0 [15:0] $end
$var wire 16 & r1 [15:0] $end
$var wire 16 ' r2 [15:0] $end
$var wire 16 ( r3 [15:0] $end
$var wire 16 ) r4 [15:0] $end
$var wire 16 * r5 [15:0] $end
$var wire 16 + r6 [15:0] $end
$var wire 16 , r7 [15:0] $end
$var wire 3 - rout [2:0] $end
$var reg 16 . buswires [15:0] $end
$upscope $end
$enddefinitions $end
$comment Show the parameter values. $end
$dumpall
$end
#0
$dumpvars
b1010101010101010 .
b0 -
b101011001111000 ,
b1001000110100 +
b1111111111111111 *
b1110111011101110 )
b1101110111011101 (
b1100110011001100 '
b1011101110111011 &
b1010101010101010 %
0$
0#
b1000100010001 "
b1010101111001101 !
$end
#2000
b1011101110111011 .
b1 -
#4000
b1100110011001100 .
b10 -
#6000
b1101110111011101 .
b11 -
#8000
b1110111011101110 .
b100 -
#10000
b1111111111111111 .
b101 -
#12000
b1001000110100 .
b110 -
#14000
b101011001111000 .
b111 -
#16000
b1010101111001101 .
b0 -
1$
#18000
b1 -
#20000
b10 -
#22000
b11 -
#24000
b100 -
#26000
b101 -
#28000
b110 -
#30000
b111 -
#32000
b1000100010001 .
b0 -
0$
1#
#34000
b1 -
#36000
b10 -
#38000
b11 -
#40000
b100 -
#42000
b101 -
#44000
b110 -
#46000
b111 -
